processgpt_agent_utils/__init__.py
processgpt_agent_utils/tools/__init__.py
processgpt_agent_utils/tools/a2a_client_tool.py
processgpt_agent_utils/tools/deterministic_code_tool.py
processgpt_agent_utils/tools/dmn_rule_tool.py
processgpt_agent_utils/tools/human_query_tool.py
processgpt_agent_utils/tools/image_manager.py
processgpt_agent_utils/tools/knowledge_manager.py
processgpt_agent_utils/tools/safe_tool_loader.py
processgpt_agent_utils/utils/__init__.py
processgpt_agent_utils/utils/context_manager.py
processgpt_agent_utils/utils/crew_event_logger.py
processgpt_agent_utils/utils/database.py
process_gpt_agent_utils-0.2.5.dist-info/METADATA
process_gpt_agent_utils-0.2.5.dist-info/WHEEL
process_gpt_agent_utils-0.2.5.dist-info/top_level.txt
process_gpt_agent_utils-0.2.5.dist-info/RECORD
