Metadata-Version: 2.4
Name: process-gpt-agent-utils
Version: 0.2.5
Summary: ProcessGPT Agent Utilities - 도구 로더, 지식 관리, 이벤트 로깅, 데이터베이스 유틸리티
License: MIT
Project-URL: Homepage, https://github.com/your-org/process-gpt-agent-utils
Project-URL: Issues, https://github.com/your-org/process-gpt-agent-utils/issues
Project-URL: Repository, https://github.com/your-org/process-gpt-agent-utils
Project-URL: Documentation, https://github.com/your-org/process-gpt-agent-utils#readme
Keywords: agent,processgpt,tools,knowledge,logging,database,crewai,mcp
Classifier: Programming Language :: Python :: 3
Classifier: Programming Language :: Python :: 3 :: Only
Classifier: License :: OSI Approved :: MIT License
Classifier: Operating System :: OS Independent
Classifier: Development Status :: 3 - Alpha
Classifier: Intended Audience :: Developers
Classifier: Topic :: Software Development :: Libraries :: Python Modules
Requires-Python: >=3.10
Requires-Dist: supabase>=2.0.0
Requires-Dist: python-dotenv>=1.0.0
Requires-Dist: mem0ai>=0.1.108
Requires-Dist: typing-extensions>=4.0.0; python_version < "3.11"
Requires-Dist: crewai<=0.175.0,>=0.152.0
Requires-Dist: crewai-tools[mcp]>=0.43.0
Requires-Dist: mcp>=1.6.0
Requires-Dist: pydantic>=2.0.0
Requires-Dist: requests>=2.25.0
Requires-Dist: pillow>=10.4.0
Requires-Dist: anyio>=3.0.0
Requires-Dist: a2a-sdk>=0.3.0
Requires-Dist: httpx>=0.24.0
Requires-Dist: vecs>=0.4.5
Provides-Extra: dev
Requires-Dist: pytest>=7.0.0; extra == "dev"
Requires-Dist: pytest-asyncio>=0.21.0; extra == "dev"
Requires-Dist: black>=22.0.0; extra == "dev"
Requires-Dist: isort>=5.10.0; extra == "dev"
Requires-Dist: mypy>=1.0.0; extra == "dev"
Requires-Dist: flake8>=5.0.0; extra == "dev"
